Metadata-Version: 1.1
Name: RevolutionSelling
Version: 0.1
Summary: a pyrogram bot cloner
Home-page: UNKNOWN
Author: Invisible Medusa
Author-email: invisiblemedusa10@gmail.com
License: MIT
Keywords: Clone
Platform: UNKNOWN
Classifier: Development Status :: 5 - Production/Stable
Classifier: Intended Audience :: Education
Classifier: Operating System :: Microsoft :: Windows :: Windows 10
Classifier: License :: OSI Approved :: MIT License
Classifier: Programming Language :: Python :: 3
